{
  "parent": "minecraft:recipes/root",
  "rewards": {
    "recipes": [
      "modernity:rock_furnace"
    ]
  },
  "criteria": {
    "has_rock": {
      "trigger": "minecraft:inventory_changed",
      "conditions": {
        "items": [
          {
            "tag": "modernity:rock"
          }
        ]
      }
    },
    "has_the_recipe": {
      "trigger": "minecraft:recipe_unlocked",
      "conditions": {
        "recipe": "modernity:rock_furnace"
      }
    }
  },
  "requirements": [
    [
      "has_rock",
      "has_the_recipe"
    ]
  ]
}